genomeworks/__init__.py
genomeworks/cuda/__init__.py
genomeworks/cuda/cuda.cpp
genomeworks/cuda/cuda.cpython-36m-x86_64-linux-gnu.so
genomeworks/cudaaligner/__init__.py
genomeworks/cudaaligner/cudaaligner.cpp
genomeworks/cudaaligner/cudaaligner.cpython-36m-x86_64-linux-gnu.so
genomeworks/cudapoa/__init__.py
genomeworks/cudapoa/cudapoa.cpp
genomeworks/cudapoa/cudapoa.cpython-36m-x86_64-linux-gnu.so
genomeworks/io/__init__.py
genomeworks/io/fastaio.py
genomeworks/io/pafio.py
genomeworks/io/utils.py
genomeworks/shared_libs/libcudaaligner.so
genomeworks/shared_libs/libcudaextender.so
genomeworks/shared_libs/libcudapoa.so
genomeworks/shared_libs/libgwbase.so
genomeworks/shared_libs/libgwio.so
genomeworks/simulators/__init__.py
genomeworks/simulators/genomesim.py
genomeworks/simulators/readsim.py
genomeworks/utilities/__init__.py
genomeworks/utilities/utilities.py
genomeworks_cuda_10_0-2021.2.0.data/data/gw_shared_objects/libcudaaligner.so
genomeworks_cuda_10_0-2021.2.0.data/data/gw_shared_objects/libcudaextender.so
genomeworks_cuda_10_0-2021.2.0.data/data/gw_shared_objects/libcudapoa.so
genomeworks_cuda_10_0-2021.2.0.data/data/gw_shared_objects/libgwbase.so
genomeworks_cuda_10_0-2021.2.0.data/data/gw_shared_objects/libgwio.so
genomeworks_cuda_10_0-2021.2.0.data/scripts/genome_simulator
genomeworks_cuda_10_0-2021.2.0.dist-info/LICENSE
genomeworks_cuda_10_0-2021.2.0.dist-info/METADATA
genomeworks_cuda_10_0-2021.2.0.dist-info/WHEEL
genomeworks_cuda_10_0-2021.2.0.dist-info/top_level.txt
genomeworks_cuda_10_0-2021.2.0.dist-info/RECORD
